swath_activations.py
missing_pixel_filler-0.0.1.dist-info/METADATA
missing_pixel_filler-0.0.1.dist-info/WHEEL
missing_pixel_filler-0.0.1.dist-info/top_level.txt
missing_pixel_filler-0.0.1.dist-info/RECORD
